setup.py
perfecto/__init__.py
perfecto/license.txt
perfecto/Exceptions/ReportingException.py
perfecto/Exceptions/__init__.py
perfecto/client/PerfectoDeprecator.py
perfecto/client/PerfectoReportiumClient.py
perfecto/client/__init__.py
perfecto/client/constants.py
perfecto/client/license.txt
perfecto/model/PerfectoExecutionContext.py
perfecto/model/__init__.py
perfecto/model/model.py
perfecto/test/TestContext.py
perfecto/test/TestResult.py
perfecto/test/TestResultFactory.py
perfecto/test/__init__.py
perfecto_py3.egg-info/PKG-INFO
perfecto_py3.egg-info/SOURCES.txt
perfecto_py3.egg-info/dependency_links.txt
perfecto_py3.egg-info/top_level.txt