Metadata-Version: 1.1
Name: perfecto-py3
Version: 0.0.2
Summary: Perfecto Reporting SDK for Python
Home-page: https://github.com/PerfectoCode
Author: Perfecto
Author-email: perfecto@perfectomobile.com
License: UNKNOWN
Download-URL: https://github.com/PerfectoCode
Keywords: Perfecto,PerfectoMobile,Reporting,Selenium,Appium,Automation testing
Platform: UNKNOWN
Classifier: Programming Language :: Python :: 3
Classifier: License :: OSI Approved :: Apache Software License
Classifier: Operating System :: OS Independent
